ros2bridge/__init__.py
ros2bridge/__main__.py
ros2bridge/py.typed
ros2bridge/ros2bridge.py
ros2bridge-0.2.6.dist-info/LICENSE
ros2bridge-0.2.6.dist-info/METADATA
ros2bridge-0.2.6.dist-info/WHEEL
ros2bridge-0.2.6.dist-info/top_level.txt
ros2bridge-0.2.6.dist-info/RECORD
