Metadata-Version: 2.1
Name: ros2bridge
Version: 0.2.6
Summary: A bridge between websocket and DDS of ROS 2
Home-page: https://github.com/bonnybabukachappilly/ros2bridge
Author: Bonny Babu
Author-email: bonnybabukachappilly@gmail.com
License: GNU GENERAL PUBLIC LICENSE Version 3
Platform: UNKNOWN
Classifier: Programming Language :: Python :: 3
Classifier: Programming Language :: Python :: 3.8
Classifier: License :: OSI Approved :: GNU General Public License v3 (GPLv3)
Classifier: Operating System :: Unix
Requires-Python: >=3.8
Requires-Dist: tornado (>=5)
Provides-Extra: dev
Requires-Dist: check-manifest (>=0.48) ; extra == 'dev'
Requires-Dist: flake8 (>=5.0) ; extra == 'dev'
Requires-Dist: mypy (>=0.982) ; extra == 'dev'
Requires-Dist: pytest-cov (>=4.0) ; extra == 'dev'
Requires-Dist: pytest (>=7.1) ; extra == 'dev'
Requires-Dist: tox (>=3.26) ; extra == 'dev'
Requires-Dist: websocket-client (>=1.4) ; extra == 'dev'
